functools2/__init__.py
functools2/async_lru.py
functools2/backends/__init__.py
functools2/backends/memory.py
functools2-0.1.1.dist-info/METADATA
functools2-0.1.1.dist-info/WHEEL
functools2-0.1.1.dist-info/RECORD
