Metadata-Version: 2.4
Name: functools2
Version: 0.1.1
Summary: Async LRU cache with TTL, singleflight, and stale-while-revalidate (SWR).
Project-URL: Homepage, https://github.com/Anaji00/functools2
Project-URL: Repository, https://github.com/Anaji00/functools2.git
Project-URL: Issues, https://github.com/Anaji00/functools2/issues
Author-email: Alessio Naji-Sepasgozar <alessionaji1@gmail.com>
License: MIT
Keywords: asyncio,cache,fastapi,lru,singleflight,swr,ttl
Classifier: License :: OSI Approved :: MIT License
Classifier: Programming Language :: Python :: 3
Classifier: Programming Language :: Python :: 3 :: Only
Classifier: Programming Language :: Python :: 3.10
Classifier: Topic :: Software Development :: Libraries
Classifier: Typing :: Typed
Requires-Python: >=3.10
